tokamak_neutron_source/__init__.py
tokamak_neutron_source/_version.py
tokamak_neutron_source/constants.py
tokamak_neutron_source/energy.py
tokamak_neutron_source/energy_data.py
tokamak_neutron_source/error.py
tokamak_neutron_source/flux.py
tokamak_neutron_source/main.py
tokamak_neutron_source/mcnp_interface.py
tokamak_neutron_source/openmc_interface.py
tokamak_neutron_source/profile.py
tokamak_neutron_source/reactions.py
tokamak_neutron_source/reactivity.py
tokamak_neutron_source/reactivity_data.py
tokamak_neutron_source/space.py
tokamak_neutron_source/tools.py
tokamak_neutron_source/transport.py
tokamak_neutron_source/data/CITATION.cff
tokamak_neutron_source/data/cross_sections/D_D_He3_n.txt
tokamak_neutron_source/data/cross_sections/D_D_T_p.txt
tokamak_neutron_source/data/cross_sections/D_He3_He_p.txt
tokamak_neutron_source/data/cross_sections/D_T_He_n.txt
tokamak_neutron_source/data/cross_sections/README.md
tokamak_neutron_source/data/cross_sections/T_T_He_2n.txt
tokamak_neutron_source/data/spectra/T_T_spectra.txt
tokamak_neutron_source-0.1.4.dist-info/METADATA
tokamak_neutron_source-0.1.4.dist-info/WHEEL
tokamak_neutron_source-0.1.4.dist-info/licenses/LICENCE
tokamak_neutron_source-0.1.4.dist-info/RECORD
