Metadata-Version: 2.4
Name: tokamak-neutron-source
Version: 0.1.4
Summary: Create an arbitrary parametric tokamak neutron source for OpenMC and MCNP
Project-URL: Source, https://github.com/Fusion-Power-Plant-Framework/tokamak-neutron-source
Project-URL: Documentation, https://github.com/Fusion-Power-Plant-Framework/tokamak-neutron-source#readme
Project-URL: Issues, https://github.com/Fusion-Power-Plant-Framework/tokamak-neutron-source/issues
Author: The tokamak neutron source team
License-Expression: LGPL-2.1-or-later
License-File: LICENCE
Classifier: Development Status :: 4 - Beta
Classifier: Intended Audience :: Science/Research
Classifier: License :: OSI Approved :: GNU Lesser General Public License v2 or later (LGPLv2+)
Classifier: Natural Language :: English
Classifier: Operating System :: OS Independent
Classifier: Topic :: Scientific/Engineering :: Physics
Classifier: Topic :: Software Development :: Libraries :: Python Modules
Requires-Python: >=3.10
Requires-Dist: babel
Requires-Dist: contourpy>=1.0
Requires-Dist: eqdsk>=0.5.0
Requires-Dist: matplotlib>=3.8
Requires-Dist: numba>=0.59
Requires-Dist: numpy>=1.26
Requires-Dist: periodictable
Requires-Dist: pint
Requires-Dist: pyyaml
Requires-Dist: scipy>=1.11.2
Provides-Extra: dev
Requires-Dist: pre-commit; extra == 'dev'
Requires-Dist: ruff; extra == 'dev'
Requires-Dist: ty; extra == 'dev'
Provides-Extra: docs
Requires-Dist: jupytext; extra == 'docs'
Requires-Dist: mkdocs; extra == 'docs'
Requires-Dist: mkdocs-gen-files; extra == 'docs'
Requires-Dist: mkdocs-jupyter; extra == 'docs'
Requires-Dist: mkdocs-literate-nav; extra == 'docs'
Requires-Dist: mkdocs-material; extra == 'docs'
Requires-Dist: mkdocs-section-index; extra == 'docs'
Requires-Dist: mkdocstrings[python]; extra == 'docs'
Provides-Extra: jetto
Requires-Dist: jetto-tools>=2.0.9; extra == 'jetto'
Provides-Extra: openmc
Requires-Dist: openmc; extra == 'openmc'
Provides-Extra: test
Requires-Dist: pytest; extra == 'test'
Requires-Dist: pytest-cov; extra == 'test'
Requires-Dist: pytest-html; extra == 'test'
Requires-Dist: pytest-json-report; extra == 'test'
Requires-Dist: pytest-metadata; extra == 'test'
